mlx_nougat/__init__.py
mlx_nougat/cli.py
mlx_nougat/convert.py
mlx_nougat/donutSwinModel.py
mlx_nougat/mbartModel.py
mlx_nougat/nougat.py
mlx_nougat/utils.py
mlx_nougat-0.1.2.dist-info/METADATA
mlx_nougat-0.1.2.dist-info/WHEEL
mlx_nougat-0.1.2.dist-info/entry_points.txt
mlx_nougat-0.1.2.dist-info/top_level.txt
mlx_nougat-0.1.2.dist-info/RECORD
