Metadata-Version: 2.1
Name: mlx_nougat
Version: 0.1.2
Summary: A CLI tool for OCR using the Nougat model
Home-page: https://github.com/mzbac/mlx_nougat
Author: anchen
Author-email: li.anchen.au@gmail.com
Classifier: Programming Language :: Python :: 3
Classifier: License :: OSI Approved :: MIT License
Classifier: Operating System :: OS Independent
Requires-Python: >=3.6
Requires-Dist: numpy
Requires-Dist: requests
Requires-Dist: pillow
Requires-Dist: transformers
Requires-Dist: wand
Requires-Dist: mlx
